mengshohuafirstmcp/__init__.py
mengshohuafirstmcp-0.1.0.dist-info/METADATA
mengshohuafirstmcp-0.1.0.dist-info/WHEEL
mengshohuafirstmcp-0.1.0.dist-info/entry_points.txt
mengshohuafirstmcp-0.1.0.dist-info/RECORD
