Metadata-Version: 2.4
Name: mengshohuafirstmcp
Version: 0.1.0
Summary: Add your description here
Author-email: Your Name <you@example.com>
Requires-Python: >=3.11
Requires-Dist: mcp[cli]>=1.9.4
